{
  "_descricao": "Lote 200 — Imobiliário/imobiliaria em Florianópolis/SC — fat baixo 4a margem 17.5% recor 40% — no_preco",
  "_preco_modificador": 1.004,
  "_distribuicao_tags": {
    "geo": "Florianópolis/SC",
    "setor_label": "Imobiliário",
    "subcategoria": "imobiliaria",
    "fat_bucket": "baixo",
    "tempo_bucket": "novo",
    "preco_bucket": "no_preco",
    "margem_calibrada": 17.5
  },
  "tipo_caso": "lote_200_anuncios",
  "identificacao": {
    "nome": "Imobiliária do Centro Florianópolis",
    "setor": "servicos_empresas",
    "subcategoria": "imobiliaria",
    "cidade": "Florianópolis",
    "estado": "SC",
    "tempo_operacao_anos": 4,
    "modelo_negocio": "b2b",
    "regime_tributario": "lucro_presumido",
    "funcionarios_clt": 3,
    "funcionarios_pj": 1
  },
  "dre": {
    "faturamento_anual": 845000,
    "faturamento_anterior": 732040,
    "cmv_pct": 13,
    "margem_operacional_pct": 17.5,
    "prolabore_mensal": 5561,
    "aluguel_mensal": 4296,
    "outros_custos_fixos": 13344
  },
  "balanco_patrimonial": {
    "ativo_imobilizado": 182137,
    "ativo_estoque": 16900,
    "ativo_caixa": 39308,
    "passivo_dividas": 93712,
    "passivo_fornecedores": 19847
  },
  "comercial": {
    "tem_recorrencia": true,
    "recorrencia_pct": 40,
    "concentracao_cliente": false,
    "num_clientes_ativos": 25,
    "ticket_medio": 5555
  },
  "gestao": {
    "processos_documentados": "nao",
    "opera_sem_dono_15dias": true,
    "tem_gerente": false,
    "equipe_permanece_apos_venda": "provavelmente"
  },
  "legal": {
    "passivo_trabalhista": false,
    "acao_judicial": false,
    "impostos_dia": "sim",
    "contabilidade_formal": true,
    "marca_registrada": true
  }
}
