{
  "_descricao": "Piloto v2 — Farmácia/farmacia em Porto Alegre/RS — fat baixo 6a target 13.0% calc 13.96% recor 15% — sobrepreco",
  "_preco_modificador": 1.261,
  "_distribuicao_tags": {
    "geo": "Porto Alegre/RS",
    "setor_label": "Farmácia",
    "subcategoria": "farmacia",
    "fat_bucket": "baixo",
    "tempo_bucket": "estabelecido",
    "preco_bucket": "sobrepreco",
    "margem_target_pct": 13.0,
    "margem_calc_pct": 13.96,
    "regime": "lucro_presumido",
    "aliq_efetiva_pct": 16.33,
    "tentativas": 7
  },
  "tipo_caso": "piloto_v2",
  "identificacao": {
    "nome": "Farmácia Saúde Porto",
    "setor": "saude",
    "subcategoria": "farmacia",
    "cidade": "Porto Alegre",
    "estado": "RS",
    "tempo_operacao_anos": 6,
    "modelo_negocio": "b2c",
    "regime_tributario": "lucro_presumido",
    "funcionarios_clt": 2,
    "funcionarios_pj": 2
  },
  "dre": {
    "faturamento_anual": 1568174,
    "faturamento_anterior": 1383968,
    "cmv_pct": 40,
    "margem_operacional_pct": 13.0,
    "prolabore_mensal": 12435,
    "aluguel_mensal": 6140,
    "outros_custos_fixos": 1737
  },
  "balanco_patrimonial": {
    "ativo_imobilizado": 295492,
    "ativo_estoque": 31363,
    "ativo_caixa": 91390,
    "passivo_dividas": 250235,
    "passivo_fornecedores": 61103
  },
  "comercial": {
    "tem_recorrencia": false,
    "recorrencia_pct": 15,
    "concentracao_cliente": false,
    "num_clientes_ativos": 3900,
    "ticket_medio": 67
  },
  "gestao": {
    "processos_documentados": "sim",
    "opera_sem_dono_15dias": true,
    "tem_gerente": true,
    "equipe_permanece_apos_venda": "provavelmente"
  },
  "legal": {
    "passivo_trabalhista": false,
    "acao_judicial": false,
    "impostos_dia": "sim",
    "contabilidade_formal": true,
    "marca_registrada": false
  }
}
