{
  "_descricao": "Piloto v2 — Academia/pilates em Vitória/ES — fat medio 7a target 17.0% calc 22.01% recor 46% — sobrepreco",
  "_preco_modificador": 1.147,
  "_distribuicao_tags": {
    "geo": "Vitória/ES",
    "setor_label": "Academia",
    "subcategoria": "pilates",
    "fat_bucket": "medio",
    "tempo_bucket": "estabelecido",
    "preco_bucket": "sobrepreco",
    "margem_target_pct": 17.0,
    "margem_calc_pct": 22.01,
    "regime": "simples",
    "aliq_efetiva_pct": 8.58,
    "tentativas": 1
  },
  "tipo_caso": "piloto_v2",
  "identificacao": {
    "nome": "Studio Pilates Equilíbrio Vitória",
    "setor": "bem_estar",
    "subcategoria": "pilates",
    "cidade": "Vitória",
    "estado": "ES",
    "tempo_operacao_anos": 7,
    "modelo_negocio": "b2c",
    "regime_tributario": "simples",
    "funcionarios_clt": 4,
    "funcionarios_pj": 1
  },
  "dre": {
    "faturamento_anual": 1062000,
    "faturamento_anterior": 909999,
    "cmv_pct": 22,
    "margem_operacional_pct": 17.0,
    "prolabore_mensal": 12592,
    "aluguel_mensal": 6009,
    "outros_custos_fixos": 6918
  },
  "balanco_patrimonial": {
    "ativo_imobilizado": 196476,
    "ativo_estoque": 21240,
    "ativo_caixa": 117148,
    "passivo_dividas": 127315,
    "passivo_fornecedores": 84555
  },
  "comercial": {
    "tem_recorrencia": true,
    "recorrencia_pct": 46,
    "concentracao_cliente": false,
    "num_clientes_ativos": 1134,
    "ticket_medio": 156
  },
  "gestao": {
    "processos_documentados": "nao",
    "opera_sem_dono_15dias": true,
    "tem_gerente": true,
    "equipe_permanece_apos_venda": "provavelmente"
  },
  "legal": {
    "passivo_trabalhista": false,
    "acao_judicial": false,
    "impostos_dia": "sim",
    "contabilidade_formal": true,
    "marca_registrada": false
  }
}
