{
  "_descricao": "Piloto v2 — Educação/idioma em Natal/RN — fat micro 3a target 17.5% calc 18.53% recor 40% — sobrepreco",
  "_preco_modificador": 1.243,
  "_distribuicao_tags": {
    "geo": "Natal/RN",
    "setor_label": "Educação",
    "subcategoria": "idioma",
    "fat_bucket": "micro",
    "tempo_bucket": "novo",
    "preco_bucket": "sobrepreco",
    "margem_target_pct": 17.5,
    "margem_calc_pct": 18.53,
    "regime": "lucro_presumido",
    "aliq_efetiva_pct": 16.33,
    "tentativas": 6
  },
  "tipo_caso": "piloto_v2",
  "identificacao": {
    "nome": "Idiomas Globalize Natal",
    "setor": "educacao",
    "subcategoria": "idioma",
    "cidade": "Natal",
    "estado": "RN",
    "tempo_operacao_anos": 3,
    "modelo_negocio": "b2c",
    "regime_tributario": "lucro_presumido",
    "funcionarios_clt": 1,
    "funcionarios_pj": 1
  },
  "dre": {
    "faturamento_anual": 425098,
    "faturamento_anterior": 400600,
    "cmv_pct": 10,
    "margem_operacional_pct": 17.5,
    "prolabore_mensal": 10116,
    "aluguel_mensal": 2405,
    "outros_custos_fixos": 2188
  },
  "balanco_patrimonial": {
    "ativo_imobilizado": 95609,
    "ativo_estoque": 8501,
    "ativo_caixa": 35831,
    "passivo_dividas": 75342,
    "passivo_fornecedores": 18878
  },
  "comercial": {
    "tem_recorrencia": true,
    "recorrencia_pct": 40,
    "concentracao_cliente": false,
    "num_clientes_ativos": 80,
    "ticket_medio": 878
  },
  "gestao": {
    "processos_documentados": "sim",
    "opera_sem_dono_15dias": false,
    "tem_gerente": true,
    "equipe_permanece_apos_venda": "provavelmente"
  },
  "legal": {
    "passivo_trabalhista": false,
    "acao_judicial": false,
    "impostos_dia": "parcelamento",
    "contabilidade_formal": true,
    "marca_registrada": true
  }
}
