{
  "_descricao": "Piloto v2 — Varejo/loja_roupas em Curitiba/PR — fat alto 27a target 7.0% calc 9.96% recor 2% — no_preco",
  "_preco_modificador": 0.963,
  "_distribuicao_tags": {
    "geo": "Curitiba/PR",
    "setor_label": "Varejo",
    "subcategoria": "loja_roupas",
    "fat_bucket": "alto",
    "tempo_bucket": "legado",
    "preco_bucket": "no_preco",
    "margem_target_pct": 7.0,
    "margem_calc_pct": 9.96,
    "regime": "simples",
    "aliq_efetiva_pct": 9.38,
    "tentativas": 3
  },
  "tipo_caso": "piloto_v2",
  "identificacao": {
    "nome": "Comércio Andrade Curitiba",
    "setor": "varejo",
    "subcategoria": "loja_roupas",
    "cidade": "Curitiba",
    "estado": "PR",
    "tempo_operacao_anos": 27,
    "modelo_negocio": "b2c",
    "regime_tributario": "simples",
    "funcionarios_clt": 13,
    "funcionarios_pj": 3
  },
  "dre": {
    "faturamento_anual": 3928870,
    "faturamento_anterior": 3439993,
    "cmv_pct": 44,
    "margem_operacional_pct": 7.0,
    "prolabore_mensal": 16162,
    "aluguel_mensal": 19614,
    "outros_custos_fixos": 7352
  },
  "balanco_patrimonial": {
    "ativo_imobilizado": 518547,
    "ativo_estoque": 294996,
    "ativo_caixa": 421285,
    "passivo_dividas": 654676,
    "passivo_fornecedores": 186317
  },
  "comercial": {
    "tem_recorrencia": false,
    "recorrencia_pct": 2,
    "concentracao_cliente": false,
    "num_clientes_ativos": 5411,
    "ticket_medio": 121
  },
  "gestao": {
    "processos_documentados": "parcial",
    "opera_sem_dono_15dias": true,
    "tem_gerente": false,
    "equipe_permanece_apos_venda": "provavelmente"
  },
  "legal": {
    "passivo_trabalhista": false,
    "acao_judicial": false,
    "impostos_dia": "sim",
    "contabilidade_formal": true,
    "marca_registrada": false
  }
}
