{
  "_descricao": "Piloto v2 — Automotivo/mecanica em São José/SC — fat baixo 4a target 15.6% calc 18.56% recor 1% — oportunidade",
  "_preco_modificador": 0.783,
  "_distribuicao_tags": {
    "geo": "São José/SC",
    "setor_label": "Automotivo",
    "subcategoria": "mecanica",
    "fat_bucket": "baixo",
    "tempo_bucket": "novo",
    "preco_bucket": "oportunidade",
    "margem_target_pct": 15.6,
    "margem_calc_pct": 18.56,
    "regime": "simples",
    "aliq_efetiva_pct": 7.61,
    "tentativas": 1
  },
  "tipo_caso": "piloto_v2",
  "identificacao": {
    "nome": "Oficina Mecânica Turbo São",
    "setor": "servicos_locais",
    "subcategoria": "mecanica",
    "cidade": "São José",
    "estado": "SC",
    "tempo_operacao_anos": 4,
    "modelo_negocio": "b2c",
    "regime_tributario": "simples",
    "funcionarios_clt": 3,
    "funcionarios_pj": 1
  },
  "dre": {
    "faturamento_anual": 727000,
    "faturamento_anterior": 631778,
    "cmv_pct": 27,
    "margem_operacional_pct": 15.6,
    "prolabore_mensal": 8112,
    "aluguel_mensal": 3906,
    "outros_custos_fixos": 800
  },
  "balanco_patrimonial": {
    "ativo_imobilizado": 155096,
    "ativo_estoque": 14540,
    "ativo_caixa": 55907,
    "passivo_dividas": 90781,
    "passivo_fornecedores": 41817
  },
  "comercial": {
    "tem_recorrencia": false,
    "recorrencia_pct": 1,
    "concentracao_cliente": false,
    "num_clientes_ativos": 215,
    "ticket_medio": 563
  },
  "gestao": {
    "processos_documentados": "parcial",
    "opera_sem_dono_15dias": true,
    "tem_gerente": true,
    "equipe_permanece_apos_venda": "provavelmente"
  },
  "legal": {
    "passivo_trabalhista": false,
    "acao_judicial": false,
    "impostos_dia": "sim",
    "contabilidade_formal": true,
    "marca_registrada": true
  }
}
